graph_visualization/__init__.py
graph_visualization/create_flask_app.py
graph_visualization/plot_graph.py
graph_visualization/tf_proto_to_json.py
graph_visualization/static/d3_graph.js
graph_visualization/templates/d3_graph.html
model_vis-0.0.22.dist-info/METADATA
model_vis-0.0.22.dist-info/WHEEL
model_vis-0.0.22.dist-info/entry_points.txt
model_vis-0.0.22.dist-info/top_level.txt
model_vis-0.0.22.dist-info/RECORD
