Metadata-Version: 2.1
Name: model-vis
Version: 0.0.22
Summary: An easy and interactive graph visualization tool for ML models!!!
Home-page: UNKNOWN
Author-email: amipro@gmail.com
License: UNKNOWN
Keywords: ML,visualization,visualize,model,graph
Platform: UNKNOWN
Requires-Python: >3.0.0
Requires-Dist: onnx (==1.6)
Requires-Dist: tensorflow (==1.14)
Requires-Dist: isort
Requires-Dist: flask
Requires-Dist: networkx
Requires-Dist: flake8
Requires-Dist: flake8-quotes
Requires-Dist: deprecated
Requires-Dist: sklearn
Requires-Dist: yapf
Requires-Dist: Flask
Requires-Dist: protobuf
Requires-Dist: absl-py
Requires-Dist: gast
Requires-Dist: astor
Requires-Dist: termcolor
Requires-Dist: keras-applications
Requires-Dist: keras-preprocessing
Requires-Dist: plotly
Requires-Dist: onnxruntime
Requires-Dist: Pillow
